tmvbeta/__init__.py
tmvbeta/py.typed
tmvbeta/tmvbeta.py
tmvbeta-1.0.1.dist-info/METADATA
tmvbeta-1.0.1.dist-info/WHEEL
tmvbeta-1.0.1.dist-info/licenses/LICENSE
tmvbeta-1.0.1.dist-info/RECORD
