Metadata-Version: 2.3
Name: tmvbeta
Version: 1.0.1
Summary: Truncated multivariate beta distribution on unit hypercube
Project-URL: Homepage, https://github.com/mifauss/TMVBeta
Project-URL: Issues, https://github.com/mifauss/TMVBeta/issues
Author-email: Michael Fauss <mfauss@ets.org>
License-File: LICENSE
Classifier: License :: OSI Approved :: MIT License
Classifier: Operating System :: OS Independent
Classifier: Programming Language :: Python :: 3
Requires-Python: >=3.10
Requires-Dist: cvxpy
Requires-Dist: gridnm
Requires-Dist: numpy
Requires-Dist: scipy
Requires-Dist: sympy
Provides-Extra: tests
Requires-Dist: pytest; extra == 'tests'
